valclient/__init__.py
valclient/auth.py
valclient/client.py
valclient/exceptions.py
valclient/resources.py
valclient-2.28.dist-info/LICENSE
valclient-2.28.dist-info/METADATA
valclient-2.28.dist-info/WHEEL
valclient-2.28.dist-info/top_level.txt
valclient-2.28.dist-info/RECORD
