Metadata-Version: 2.1
Name: valclient
Version: 2.28
Summary: Wrapper for VALORANT's client API
Home-page: https://github.com/colinhartigan/valclient.py
Author: colinh
License: UNKNOWN
Project-URL: Bug Tracker, https://github.com/colinhartigan/valclient.py/issues
Platform: UNKNOWN
Classifier: Programming Language :: Python :: 3
Classifier: License :: OSI Approved :: MIT License
Classifier: Operating System :: OS Independent
Requires-Python: >=3.0
License-File: LICENSE
